cell_dynamics/__init__.py
cell_dynamics-0.0.0.dist-info/METADATA
cell_dynamics-0.0.0.dist-info/WHEEL
cell_dynamics-0.0.0.dist-info/top_level.txt
cell_dynamics-0.0.0.dist-info/RECORD
