Metadata-Version: 2.1
Name: cell-dynamics
Version: 0.0.0
Summary: Cell dynamics library.
Home-page: https://github.com/mvinyard/cell_dynamics
Author: Michael E. Vinyard - Harvard University - Massachussetts General Hospital - Broad Institute of MIT and Harvard
Author-email: mvinyard@broadinstitute.org
License: MIT
Platform: UNKNOWN
Classifier: Development Status :: 2 - Pre-Alpha
Classifier: Programming Language :: Python :: 3.6
Classifier: Intended Audience :: Science/Research
Classifier: Topic :: Scientific/Engineering :: Bio-Informatics
Requires-Python: >3.6.0
